setup.cfg
setup.py
kissxml/__init__.py
kissxml/_xml.py
kissxml/parser.py
kissxml.egg-info/PKG-INFO
kissxml.egg-info/SOURCES.txt
kissxml.egg-info/dependency_links.txt
kissxml.egg-info/top_level.txt