Metadata-Version: 1.0
Name: kissxml
Version: 0.1
Summary: A very simple XML manipulation.
Home-page: https://github.com/joestump/kissxml
Author: Joseph C. Stump
Author-email: joe@stu.mp
License: UNKNOWN
Platform: UNKNOWN
Classifier: Development Status :: 4 - Beta
Classifier: License :: OSI Approved :: MIT License
Classifier: Operating System :: OS Independent
